Metadata-Version: 1.0
Name: CGBp-dist
Version: 1.2
Summary: Gaussian and Binomial distributions
Home-page: UNKNOWN
Author: Vy Thuy Nguyen
Author-email: thuyvy11998@gmail.com
License: UNKNOWN
Platform: UNKNOWN
